delierium/DerivativeOperators.py
delierium/Infinitesimals.py
delierium/__init__.py
delierium/helpers.py
delierium-0.9.0.dev10.dist-info/LICENSE
delierium-0.9.0.dev10.dist-info/METADATA
delierium-0.9.0.dev10.dist-info/WHEEL
delierium-0.9.0.dev10.dist-info/top_level.txt
delierium-0.9.0.dev10.dist-info/RECORD
