Metadata-Version: 2.1
Name: delierium
Version: 0.9.0.dev10
Summary: Symmetry Analysis for ODEs/PDEs using SageMath
Home-page: UNKNOWN
Author: Martin Mayerhofer-Schöpf
Author-email: tapir@aon.at
License: MIT
Project-URL: Source, https://github.com/tapir442/delierium
Keywords: ODE PDE Lie Symmetry
Platform: UNKNOWN
Classifier: Development Status :: 3 - Alpha
Classifier: Programming Language :: Python :: 3 :: Only
Classifier: License :: OSI Approved :: MIT License
Classifier: Intended Audience :: Science/Research
Classifier: Topic :: Scientific/Engineering :: Mathematics
Requires-Python: >=3.10
License-File: LICENSE
Requires-Dist: anytree
Requires-Dist: more-itertools
